dyad_cli/__init__.py
dyad_cli/py.typed
dyad_cli/user_data_dir_utils.py
dyad_cli/version.py
dyad_cli-0.1.0.dist-info/METADATA
dyad_cli-0.1.0.dist-info/WHEEL
dyad_cli-0.1.0.dist-info/entry_points.txt
dyad_cli-0.1.0.dist-info/RECORD
